apluslms_yamlidator/__init__.py
apluslms_yamlidator/document.py
apluslms_yamlidator/schemas.py
apluslms_yamlidator/validator.py
apluslms_yamlidator/utils/__init__.py
apluslms_yamlidator/utils/collections.py
apluslms_yamlidator/utils/decorator.py
apluslms_yamlidator/utils/error_render.py
apluslms_yamlidator/utils/functional.py
apluslms_yamlidator/utils/module_resources.py
apluslms_yamlidator/utils/translation.py
apluslms_yamlidator/utils/version.py
apluslms_yamlidator/utils/yaml.py
apluslms_yamlidator-0.3.0rc1.dist-info/LICENSE
apluslms_yamlidator-0.3.0rc1.dist-info/METADATA
apluslms_yamlidator-0.3.0rc1.dist-info/WHEEL
apluslms_yamlidator-0.3.0rc1.dist-info/top_level.txt
apluslms_yamlidator-0.3.0rc1.dist-info/RECORD
